api/__init__.py
api/get_imgs_by_key.py
core/__init__.py
core/api_client.py
coze_api_toolkit/__init__.py
coze_api_toolkit/api/__init__.py
coze_api_toolkit/api/get_imgs_by_key.py
coze_api_toolkit/config/api_catalog.json
coze_api_toolkit/core/__init__.py
coze_api_toolkit/core/api_client.py
utils/__init__.py
coze_api_toolkit-0.1.0.dist-info/LICENSE
coze_api_toolkit-0.1.0.dist-info/METADATA
coze_api_toolkit-0.1.0.dist-info/WHEEL
coze_api_toolkit-0.1.0.dist-info/top_level.txt
coze_api_toolkit-0.1.0.dist-info/RECORD
