Metadata-Version: 2.1
Name: coze-api-toolkit
Version: 0.1.0
Summary: 基于 Coze 工作流 API 的简化 Python 工具包
Home-page: https://github.com/your-username/coze-api-toolkit
Author: Coze API Toolkit Team
Author-email: your-email@example.com
Classifier: Programming Language :: Python :: 3
Classifier: Programming Language :: Python :: 3.7
Classifier: Programming Language :: Python :: 3.8
Classifier: Programming Language :: Python :: 3.9
Classifier: Programming Language :: Python :: 3.10
Classifier: License :: OSI Approved :: MIT License
Classifier: Operating System :: OS Independent
Requires-Python: >=3.7
License-File: LICENSE
Requires-Dist: cozepy>=1.0.0
Requires-Dist: requests>=2.28.0
Requires-Dist: pillow>=9.0.0
